metrics_as_scores/__init__.py
metrics_as_scores/__version__.py
metrics_as_scores/cli/__init__.py
metrics_as_scores/cli/BundleOwn.py
metrics_as_scores/cli/Cli.py
metrics_as_scores/cli/CreateDataset.py
metrics_as_scores/cli/Download.py
metrics_as_scores/cli/FitParametric.py
metrics_as_scores/cli/GenerateDensities.py
metrics_as_scores/cli/helpers.py
metrics_as_scores/cli/KnownDatasets.py
metrics_as_scores/cli/LocalDatasets.py
metrics_as_scores/cli/LocalWebserver.py
metrics_as_scores/cli/MainWorkflow.py
metrics_as_scores/cli/Workflow.py
metrics_as_scores/data/__init__.py
metrics_as_scores/data/pregenerate.py
metrics_as_scores/data/pregenerate_distns.py
metrics_as_scores/data/pregenerate_fit.py
metrics_as_scores/datasets/_default/_quarto.yml
metrics_as_scores/datasets/_default/About.qmd
metrics_as_scores/datasets/_default/readme.md
metrics_as_scores/datasets/_default/refs.bib
metrics_as_scores/datasets/_default/web/about.html
metrics_as_scores/datasets/_default/web/references.html
metrics_as_scores/datasets/known-datasets.bib
metrics_as_scores/datasets/known-datasets.json
metrics_as_scores/distribution/__init__.py
metrics_as_scores/distribution/distribution.py
metrics_as_scores/distribution/fitting.py
metrics_as_scores/distribution/fitting_problems.py
metrics_as_scores/pyproject.toml
metrics_as_scores/tools/__init__.py
metrics_as_scores/tools/funcs.py
metrics_as_scores/tools/lazy.py
metrics_as_scores/webapp/__init__.py
metrics_as_scores/webapp/app_hooks.py
metrics_as_scores/webapp/data.py
metrics_as_scores/webapp/exception.py
metrics_as_scores/webapp/footer.html
metrics_as_scores/webapp/header.html
metrics_as_scores/webapp/main.py
metrics_as_scores/webapp/metrics-as-scores.nginx.conf
metrics_as_scores/webapp/metrics-as-scores.service
metrics_as_scores/webapp/readme.md
metrics_as_scores/webapp/static/curve.ico
metrics_as_scores/webapp/static/curve.png
metrics_as_scores/webapp/static/loading.png
metrics_as_scores/webapp/static/main.js
metrics_as_scores-2.8.2.dist-info/entry_points.txt
metrics_as_scores-2.8.2.dist-info/LICENSE
metrics_as_scores-2.8.2.dist-info/METADATA
metrics_as_scores-2.8.2.dist-info/WHEEL
metrics_as_scores-2.8.2.dist-info/RECORD
