Metadata-Version: 2.1
Name: metrics-as-scores
Version: 2.8.2
Summary: Interactive web application, tool- and analysis suite for approximating, exploring, understanding, and sampling from conditional distributions.
Home-page: https://github.com/mrshoenel/metrics-as-scores
License: Dual-licensed under GNU General Public License v3 (GPLv3) and closed-source
Keywords: distribution fitting,statistical tests,context-dependent,metrics,quality,score
Author: Sebastian Hönel
Author-email: development@hoenel.net
Requires-Python: >=3.10,<3.12
Classifier: Development Status :: 5 - Production/Stable
Classifier: Environment :: Web Environment
Classifier: Intended Audience :: Education
Classifier: Intended Audience :: End Users/Desktop
Classifier: Intended Audience :: Science/Research
Classifier: License :: OSI Approved :: GNU General Public License v3 (GPLv3)
Classifier: License :: Other/Proprietary License
Classifier: Operating System :: OS Independent
Classifier: Programming Language :: Python :: 3
Classifier: Programming Language :: Python :: 3.10
Classifier: Programming Language :: Python :: 3.11
Classifier: Programming Language :: Python :: 3
Classifier: Topic :: Utilities
Requires-Dist: Sphinx (>=5.3.0,<6.0.0)
Requires-Dist: StrEnum (>=0.4.8,<0.5.0)
Requires-Dist: bokeh (>=2.4.3,<3.0.0)
Requires-Dist: joblib (>=1.2.0,<2.0.0)
Requires-Dist: jupyterlab (>=3.4.7,<4.0.0)
Requires-Dist: matplotlib (>=3.6.0,<4.0.0)
Requires-Dist: myst-parser (>=1.0.0,<2.0.0)
Requires-Dist: nptyping (>=2.4.1,<3.0.0)
Requires-Dist: poethepoet (>=0.18.1,<0.19.0)
Requires-Dist: ptvsd (>=4.3.2,<5.0.0)
Requires-Dist: pymoo (>=0.6.0,<0.7.0)
Requires-Dist: pytest-cov (>=4.0.0,<5.0.0)
Requires-Dist: questionary (>=1.10.0,<2.0.0)
Requires-Dist: rich (>=13.3.1,<14.0.0)
Requires-Dist: scikit-learn (>=1.2.1,<2.0.0)
Requires-Dist: scipy (>=1.10.1,<2.0.0)
Requires-Dist: sphinx-rtd-theme (>=1.1.1,<2.0.0)
Requires-Dist: statsmodels (>=0.13.2,<0.14.0)
Requires-Dist: tabulate (>=0.9.0,<0.10.0)
Requires-Dist: toml (>=0.10.2,<0.11.0)
Requires-Dist: tqdm (>=4.64.1,<5.0.0)
Requires-Dist: wget (>=3.2,<4.0)
Project-URL: Repository, https://github.com/mrshoenel/metrics-as-scores/issues
